{
    "name": "sex_frac_50",
    "start time": "2023-01-18 10:16:54.432611",
    "attack_config": {
        "train_config": {
            "data_config": {
                "name": "new_census",
                "prop": "sex",
                "value": 0.5,
                "split": "victim",
                "drop_senstive_cols": false,
                "scale": 1.0,
                "augment": false,
                "classify": null,
                "cwise_samples": null,
                "squeeze": true,
                "processed_variant": true,
                "prune": 0,
                "adv_use_frac": 0.5
            },
            "epochs": 0,
            "learning_rate": 0.0,
            "batch_size": 0,
            "misc_config": null,
            "lr_scheduler": null,
            "verbose": false,
            "num_models": 1,
            "offset": 0,
            "weight_decay": 0,
            "get_best": true,
            "cpu": false,
            "expect_extra": true,
            "save_every_epoch": false,
            "extra_info": null,
            "regression": false,
            "multi_class": false,
            "label_noise": 0,
            "model_arch": null,
            "parallel": false,
            "early_stopping": null
        },
        "values": [
            0.0,
            0.1,
            0.2,
            0.3,
            0.4,
            0.6,
            0.7,
            0.8,
            0.9,
            1.0
        ],
        "black_box": {
            "attack_type": [
                "KL"
            ],
            "ratios": [
                1.0
            ],
            "batch_size": 30000,
            "num_adv_models": 50,
            "granularity": 0.05,
            "preload": true,
            "multi": null,
            "multi2": null,
            "multi_class": false,
            "save": false,
            "tune_final_threshold": false,
            "Start_epoch": 1,
            "End_epoch": 20,
            "relative_threshold": false,
            "loss_variant": false,
            "random_order": false,
            "log_odds_order": false,
            "kl_frac": 0.8,
            "kl_voting": false,
            "generative_attack": null,
            "order_name": null,
            "geo_mean": false,
            "regression_config": null,
            "merlin_mean": 0.0,
            "merlin_std": 0.3,
            "merlin_neighbors": 100
        },
        "white_box": null,
        "tries": 5,
        "num_victim_models": 250,
        "on_cpu": false,
        "adv_misc_config": null,
        "num_total_adv_models": 1000,
        "victim_local_attack": false,
        "victim_model_arch": null,
        "adv_model_arch": null,
        "adv_processed_variant": false,
        "adv_target_epoch": null,
        "victim_target_epoch": null
    },
    "result": {
        "KL": {
            "0.0": {
                "adv_acc": [
                    null,
                    null,
                    null,
                    null,
                    null
                ],
                "victim_acc": [
                    100.0,
                    100.0,
                    100.0,
                    100.0,
                    100.0
                ]
            },
            "0.1": {
                "adv_acc": [
                    null,
                    null,
                    null,
                    null,
                    null
                ],
                "victim_acc": [
                    87.0,
                    90.60000000000001,
                    92.2,
                    88.0,
                    87.0
                ]
            },
            "0.2": {
                "adv_acc": [
                    null,
                    null,
                    null,
                    null,
                    null
                ],
                "victim_acc": [
                    74.0,
                    70.19999999999999,
                    80.0,
                    72.39999999999999,
                    69.39999999999999
                ]
            },
            "0.3": {
                "adv_acc": [
                    null,
                    null,
                    null,
                    null,
                    null
                ],
                "victim_acc": [
                    59.8,
                    68.4,
                    64.4,
                    62.2,
                    62.0
                ]
            },
            "0.4": {
                "adv_acc": [
                    null,
                    null,
                    null,
                    null,
                    null
                ],
                "victim_acc": [
                    51.4,
                    53.400000000000006,
                    56.8,
                    51.4,
                    54.0
                ]
            },
            "0.6": {
                "adv_acc": [
                    null,
                    null,
                    null,
                    null,
                    null
                ],
                "victim_acc": [
                    56.99999999999999,
                    57.4,
                    56.99999999999999,
                    54.400000000000006,
                    47.199999999999996
                ]
            },
            "0.7": {
                "adv_acc": [
                    null,
                    null,
                    null,
                    null,
                    null
                ],
                "victim_acc": [
                    68.2,
                    67.4,
                    62.6,
                    68.4,
                    70.19999999999999
                ]
            },
            "0.8": {
                "adv_acc": [
                    null,
                    null,
                    null,
                    null,
                    null
                ],
                "victim_acc": [
                    84.0,
                    77.8,
                    85.2,
                    78.8,
                    82.8
                ]
            },
            "0.9": {
                "adv_acc": [
                    null,
                    null,
                    null,
                    null,
                    null
                ],
                "victim_acc": [
                    93.8,
                    91.60000000000001,
                    96.6,
                    95.0,
                    92.4
                ]
            },
            "1.0": {
                "adv_acc": [
                    null,
                    null,
                    null,
                    null,
                    null
                ],
                "victim_acc": [
                    100.0,
                    100.0,
                    100.0,
                    100.0,
                    100.0
                ]
            }
        }
    },
    "save time": "2023-01-18 12:42:26.525266"
}